Metadata-Version: 2.1
Name: openfoamparser-mai
Version: 0.14
Summary: Lightweight library to parse OpenFOAM files using Numpy (Ofpp Fork)
Home-page: https://www.ccs-labs.org/
Author: CCS-Labs
Author-email: vadim@phygitalism.com
License: UNKNOWN
Project-URL: Parent Project Description, https://www.forschung-it-sicherheit-kommunikationssysteme.de/projekte/mamoko
Project-URL: Source, https://github.com/resi2311/openfoamparser.git
Project-URL: Forked from, https://github.com/ApolloLV/openfoamparser
Keywords: openfoam cfd parser
Platform: UNKNOWN
Classifier: Development Status :: 4 - Beta
Classifier: Intended Audience :: Science/Research
Classifier: Topic :: Scientific/Engineering
Classifier: License :: OSI Approved :: MIT License
Classifier: Programming Language :: Python :: 3
Classifier: Programming Language :: Python :: 3.5
Classifier: Programming Language :: Python :: 3.6
Classifier: Programming Language :: Python :: 3.7
Requires-Python: >=3.7
